BSSD_derivation_for_Lanelet2/BSSD_elements.py
BSSD_derivation_for_Lanelet2/__init__.py
BSSD_derivation_for_Lanelet2/__main__.py
BSSD_derivation_for_Lanelet2/behavior_derivation.py
BSSD_derivation_for_Lanelet2/constants.py
BSSD_derivation_for_Lanelet2/data_handler.py
BSSD_derivation_for_Lanelet2/geometry_derivation.py
BSSD_derivation_for_Lanelet2/io_handler.py
BSSD_derivation_for_Lanelet2/preprocessing.py
BSSD_derivation_for_Lanelet2/util.py
lanelet2_bssd_converter-2025.1.dist-info/LICENSE
lanelet2_bssd_converter-2025.1.dist-info/METADATA
lanelet2_bssd_converter-2025.1.dist-info/WHEEL
lanelet2_bssd_converter-2025.1.dist-info/entry_points.txt
lanelet2_bssd_converter-2025.1.dist-info/top_level.txt
lanelet2_bssd_converter-2025.1.dist-info/RECORD
