Metadata-Version: 2.1
Name: lanelet2-bssd-converter
Version: 2025.1
Summary: Tool for the automated generation of the BSSD extension based on Lanelet2 maps
Author-email: "Institute of Automotive Engineering, Technical University of Darmstadt" <open-source@fzd.tu-darmstadt.de>
Maintainer-email: "Institute of Automotive Engineering, Technical University of Darmstadt" <open-source@fzd.tu-darmstadt.de>
License: Copyright 2024 Institute of Automotive Engineering (FZD), Technical University of Darmstadt
Project-URL: BSSD-Homepage, https://gitlab.com/tuda-fzd/scenery-representations-and-maps/behavior-semantic-scenery-description
Project-URL: Repository, https://gitlab.com/tuda-fzd/scenery-representations-and-maps/lanelet2-bssd-converter
Keywords: automated driving,BSSD,Lanelet2,OSM
Classifier: License :: OSI Approved :: MIT License
Classifier: Programming Language :: Python
Classifier: Programming Language :: Python :: 3
Requires-Python: >=3.8
License-File: LICENSE
Requires-Dist: numpy>=1.22.3
Requires-Dist: osmium>=3.2.0
Requires-Dist: bssd-core>=0.1.0
Provides-Extra: dev
Requires-Dist: pytest; extra == "dev"
